wildwood/.DS_Store
wildwood/__init__.py
wildwood/_grow.py
wildwood/_impurity.py
wildwood/_node.py
wildwood/_split.py
wildwood/_tree.py
wildwood/_tree_context.py
wildwood/_utils.py
wildwood/datasets/.DS_Store
wildwood/datasets/__init__.py
wildwood/datasets/_adult.py
wildwood/datasets/_amazon.py
wildwood/datasets/_bank.py
wildwood/datasets/_car.py
wildwood/datasets/_default_cb.py
wildwood/datasets/_epsilon.py
wildwood/datasets/_higgs.py
wildwood/datasets/_internet.py
wildwood/datasets/_kick.py
wildwood/datasets/_utils.py
wildwood/datasets/data/boston.csv.gz
wildwood/datasets/data/cardiotocography.csv.gz
wildwood/datasets/data/churn.csv.gz
wildwood/datasets/data/letor.csv.gz
wildwood/datasets/data/letter.csv.gz
wildwood/datasets/data/satimage.csv.gz
wildwood/datasets/data/sensorless.csv.gz
wildwood/datasets/data/spambase.csv.gz
wildwood/datasets/dataset.py
wildwood/datasets/loaders.py
wildwood/datasets/signals.py
wildwood/forest.py
wildwood/plot.py
wildwood/preprocessing/__init__.py
wildwood/preprocessing/_binning.py
wildwood/preprocessing/_checks.py
wildwood/preprocessing/encoder.py
wildwood/preprocessing/features_bitarray.py
wildwood/tree.py
wildwood-0.3.dist-info/LICENSE
wildwood-0.3.dist-info/METADATA
wildwood-0.3.dist-info/WHEEL
wildwood-0.3.dist-info/RECORD
