Metadata-Version: 2.1
Name: wildwood
Version: 0.3
Summary: scikit-learn compatible alternative random forests algorithms
Home-page: https://wildwood.readthedocs.io
Keywords: python,machine-learning,classification,regression,random-forests,robust-methods
Author: Stéphane Gaïffas
Author-email: stephane.gaiffas@gmail.com
Requires-Python: >=3.8,<4.0
Classifier: Development Status :: 3 - Alpha
Classifier: Intended Audience :: Developers
Classifier: Intended Audience :: Science/Research
Classifier: License :: OSI Approved :: BSD License
Classifier: Operating System :: POSIX
Classifier: Operating System :: Unix
Classifier: Programming Language :: Python
Classifier: Programming Language :: Python :: 3
Classifier: Programming Language :: Python :: 3.8
Classifier: Programming Language :: Python :: 3.9
Classifier: Programming Language :: Python :: 3.10
Classifier: Programming Language :: Python :: 3.11
Classifier: Programming Language :: Python :: 3.12
Classifier: Topic :: Software Development :: Libraries :: Python Modules
Requires-Dist: matplotlib (>=3.7)
Requires-Dist: numba (>=0.58)
Requires-Dist: numpy (>=1.24)
Requires-Dist: pandas (>=2.0)
Requires-Dist: scikit-learn (>=1.3)
Requires-Dist: scipy (>=1.9)
Requires-Dist: tqdm (>=4.36)
Requires-Dist: xlrd (>=2.0)
Project-URL: Documentation, https://wildwood.readthedocs.io
Project-URL: Repository, https://github.com/pyensemble/wildwood
